productml/__init__.py
productml/setup.py
productml/data/__init__.py
productml/data/labelling/__init__.py
productml/data/labelling/text_matching.py
productml/data/vision/__init__.py
productml-0.0.4.dist-info/METADATA
productml-0.0.4.dist-info/WHEEL
productml-0.0.4.dist-info/top_level.txt
productml-0.0.4.dist-info/RECORD
