Metadata-Version: 2.1
Name: productml
Version: 0.0.4
Summary: Library for Akumyn product-level inference.
Home-page: UNKNOWN
Author: DevsDoData
Author-email: jerryyexu@gmail.com
License: MIT
Keywords: retail,ml,cv,devsdodata
Platform: UNKNOWN
Classifier: Development Status :: 3 - Alpha
Classifier: Intended Audience :: Developers
Classifier: License :: OSI Approved :: MIT License
Classifier: Programming Language :: Python :: 3
Requires-Python: >=3.7
